CHANGES.rst
MANIFEST.in
README.rst
setup.cfg
setup.py
nensskel/__init__.py
nensskel/cmdline.py
nensskel/djangoapp.py
nensskel/library.py
nensskel/lizardsite.py
nensskel/smoketest.rst
nensskel/smoketest_fixt.py
nensskel/utils.py
nensskel.egg-info/PKG-INFO
nensskel.egg-info/SOURCES.txt
nensskel.egg-info/dependency_links.txt
nensskel.egg-info/entry_points.txt
nensskel.egg-info/not-zip-safe
nensskel.egg-info/requires.txt
nensskel.egg-info/top_level.txt
nensskel/templates/djangoapp/bower.json_tmpl
nensskel/templates/djangoapp/buildout.cfg_tmpl
nensskel/templates/djangoapp/setup.py_tmpl
nensskel/templates/djangoapp/+dot+tx/config_tmpl
nensskel/templates/djangoapp/+package+/admin.py_tmpl
nensskel/templates/djangoapp/+package+/models.py
nensskel/templates/djangoapp/+package+/tests.py
nensskel/templates/djangoapp/+package+/testsettings.py_tmpl
nensskel/templates/djangoapp/+package+/urls.py_tmpl
nensskel/templates/djangoapp/+package+/views.py_tmpl
nensskel/templates/djangoapp/+package+/fixtures/README.rst
nensskel/templates/djangoapp/+package+/locale/en/LC_MESSAGES/django.po
nensskel/templates/djangoapp/+package+/static/+package+/README.rst
nensskel/templates/djangoapp/+package+/templates/+package+/README.rst
nensskel/templates/library/+dot+coveragerc_tmpl
nensskel/templates/library/+dot+gitignore_tmpl
nensskel/templates/library/CHANGES.rst_tmpl
nensskel/templates/library/LICENSE.rst
nensskel/templates/library/MANIFEST.in_tmpl
nensskel/templates/library/README.rst_tmpl
nensskel/templates/library/bootstrap.py
nensskel/templates/library/buildout.cfg_tmpl
nensskel/templates/library/monkeypatch_setuptools.py
nensskel/templates/library/setup.cfg_tmpl
nensskel/templates/library/setup.py_tmpl
nensskel/templates/library/+package+/__init__.py
nensskel/templates/library/doc/source/code.rst_tmpl
nensskel/templates/library/doc/source/conf.py_tmpl
nensskel/templates/library/doc/source/index.rst
nensskel/templates/library/doc/source/project.rst
nensskel/templates/lizardsite/+dot+gitignore_tmpl
nensskel/templates/lizardsite/README.rst_tmpl
nensskel/templates/lizardsite/development.cfg_tmpl
nensskel/templates/lizardsite/production.cfg_tmpl
nensskel/templates/lizardsite/server.cfg_tmpl
