Metadata-Version: 1.0
Name: nensskel
Version: 1.37
Summary: Skeleton for Nelen & Schuurmans projects
Home-page: http://pypi.python.org/pypi/nensskel
Author: Reinout van Rees
Author-email: reinout.vanrees@nelen-schuurmans.nl
License: GPL
Platform: UNKNOWN
